<rom>
	<romid>
		<xmlid>EZ1GB10H</xmlid>
		<internalidaddress>2004</internalidaddress>
		<internalidstring>EZ1GB10H</internalidstring>
		<ecuid>6E12148007</ecuid>
		<make>Subaru</make>
		<market>USDM</market>
		<model>Impreza</model>
		<submodel>2.5i</submodel>
		<transmission>AT</transmission>
		<year>10</year>
		<flashmethod>subarucan</flashmethod>
		<memmodel>SH7058</memmodel>
		<checksummodule>subarudbw</checksummodule>
	</romid>

	<include>32BITBASE</include>

	<table name="AVLS_Minimum_ECT_Switch_TPS_Mode_B" address="d22b8" type="X Axis" elements="2" scaling="RPM"/>

	<table name="AVLS_Minimum_Oil_Temperature_High_Mode_Switch" address="d22d8" type="X Axis" elements="1" scaling="RPM"/>

	<table name="AVLS_Minimum_RPM_High_Mode_A" address="d22ec" type="X Axis" elements="2" scaling="RPM"/>

	<table name="AVLS_Minimum_RPM_High_Mode_B" address="d22f4" type="X Axis" elements="2" scaling="RPM"/>

	<table name="AVLS_Minimum_RPM_High_Mode_C" address="d22fc" type="X Axis" elements="2" scaling="RPM"/>

	<table name="AVLS_Minimum_RPM_High_Mode_D" address="d22d0" type="X Axis" elements="2" scaling="RPM"/>

	<table name="AVLS_Minimum_Run_Time_High_Mode_On" address="d229e" type="X Axis" elements="1" scaling="Knock2"/>

	<table name="AVLS_TPS_Mode_Switch_Hysteresis" address="d22c8" type="X Axis" elements="1" scaling="RPM"/>

	<table name="AVLS_TPS_Required_High_Mode_Switchover_A" category="Misc" address="d2570" type="2D" level="1" scaling="ThrottlePlateOpeningAngle(%)2">
		<table name="Engine Speed" address="d2554" type="Y Axis" elements="7" scaling="RPM"/>
	</table>

	<table name="AVLS_TPS_Required_High_Mode_Switchover_B_Cold" category="Misc" address="d2500" type="2D" level="1" scaling="ThrottlePlateOpeningAngle(%)2">
		<table name="Engine Speed" address="d24e4" type="Y Axis" elements="7" scaling="RPM"/>
	</table>

	<table name="AVLS_TPS_Required_High_Mode_Switchover_B_Warm" category="Misc" address="d2538" type="2D" level="1" scaling="ThrottlePlateOpeningAngle(%)2">
		<table name="Engine Speed" address="d251c" type="Y Axis" elements="7" scaling="RPM"/>
	</table>

	<table name="Manifold Pressure Sensor Scaling_" address="d1520">
	</table>

	<table name="Manifold Pressure Sensor Limits (CEL)" address="d14ec">
	</table>

	<table name="Manifold Pressure Sensor CEL Delays" address="c39a3">
	</table>

	<table name="Primary Open Loop Fueling A" address="c9df8">
		<table name="Engine Load" address="c9da4" elements="11"/>
		<table name="Engine Speed" address="c9dd0" elements="10"/>
	</table>

	<table name="Primary Open Loop Fueling B" address="c9ec8">
		<table name="Engine Load" address="c9e68" elements="11"/>
		<table name="Engine Speed" address="c9e94" elements="13"/>
	</table>

	<table name="Minimum Active Primary Open Loop Enrichment" address="c70b0">
	</table>

	<table name="Front Oxygen Sensor Scaling" address="d1a4c">
		<table name="Front Oxygen Sensor" address="d1a18"/>
	</table>

	<table name="Front Oxygen Sensor Rich Limit" address="1f36c">
	</table>

	<table name="Front Oxygen Sensor Compensation (Atm. Pressure)" address="c2734">
		<table name="Atmospheric Pressure" address="c2724"/>
	</table>

	<table name="CL Fueling Target Compensation A (Load)" address="ca6ec">
		<table name="Engine Load" address="ca674"/>
		<table name="Engine Speed" address="ca6a0" elements="19"/>
	</table>

	<table name="CL Fueling Target Compensation B (Load)" address="cab24">
		<table name="Engine Load" address="caaac"/>
		<table name="Engine Speed" address="caad8" elements="19"/>
	</table>

	<table name="CL Fueling Target Compensation C (Load)" address="caf5c">
		<table name="Engine Load" address="caee4"/>
		<table name="Engine Speed" address="caf10" elements="19"/>
	</table>

	<table name="CL Fueling Target Compensation D (Load)" address="cb394">
		<table name="Engine Load" address="cb31c"/>
		<table name="Engine Speed" address="cb348" elements="19"/>
	</table>

	<table name="CL Fueling Target Compensation (ECT)" address="ca614">
		<table name="Coolant Temperature" address="c73fc"/>
		<table name="Engine Load" address="ca608"/>
	</table>

	<table name="CL Fueling Target Compensation (ECT) Disable" address="c6f04">
	</table>

	<table name="CL to OL Delay A (Atm. Pressure)" address="c8ca4">
		<table name="Atmospheric Pressure" address="c8c88"/>
	</table>

	<table name="CL to OL Delay B (Atm. Pressure)" address="c8cd0">
		<table name="Atmospheric Pressure" address="c8cb4"/>
	</table>

	<table name="CL to OL Transition with Delay (Accelerator)" address="c7a08">
		<table name="Engine Speed" address="c79c8"/>
	</table>

	<table name="CL to OL Transition with Delay Throttle Hysteresis" address="c70b4">
	</table>

	<table name="CL to OL Transition with Delay (Base Pulse Width)" address="c8c68">
		<table name="Engine Speed" address="c8c28"/>
	</table>

	<table name="CL to OL Transition with Delay BPW Hysteresis" address="c70b8">
	</table>

	<table name="CL Delay Minimum (ECT)" address="c70bc">
	</table>

	<table name="CL Delay Maximum Engine Speed A" address="c70c8">
	</table>

	<table name="CL Delay Maximum Engine Speed B" address="c70c4">
	</table>

	<table name="CL Delay Engine Speed B Counter Threshold" address="c6c4e">
	</table>

	<table name="CL Delay Maximum (Throttle) A" address="c70c0">
	</table>

	<table name="CL Delay Throttle A Counter Threshold" address="c6c4c">
	</table>

	<table name="CL Delay Maximum (Throttle) B (ECT)" address="c7a18">
		<table name="Coolant Temperature" address="c73fc"/>
	</table>

	<table name="Injector Latency_" address="ca430">
		<table name="Battery Output" address="ca410"/>
		<table name="Manifold Pressure" address="ca424"/>
	</table>

	<table name="Injector Flow Scaling" address="c6dc0">
	</table>

	<table name="Per Injector Pulse Width Compensation A" address="c9fe0">
		<table name="Last Calculated Base Pulse Width" address="c9fa4" elements="8"/>
		<table name="Engine Speed" address="c9fc4" elements="7"/>
	</table>

	<table name="Per Injector Pulse Width Compensation B" address="ca054">
		<table name="Last Calculated Base Pulse Width" address="ca018" elements="8"/>
		<table name="Engine Speed" address="ca038" elements="7"/>
	</table>

	<table name="Per Injector Pulse Width Compensation C" address="ca0c8">
		<table name="Last Calculated Base Pulse Width" address="ca08c" elements="8"/>
		<table name="Engine Speed" address="ca0ac" elements="7"/>
	</table>

	<table name="Per Injector Pulse Width Compensation D" address="ca13c">
		<table name="Last Calculated Base Pulse Width" address="ca100" elements="8"/>
		<table name="Engine Speed" address="ca120" elements="7"/>
	</table>

	<table name="Cranking Fuel Injector Pulse Width A (ECT)" address="c7d36">
		<table name="Coolant Temperature" address="c73fc"/>
	</table>

	<table name="Cranking Fuel Injector Pulse Width B (ECT)" address="c7d56">
		<table name="Coolant Temperature" address="c73fc"/>
	</table>

	<table name="Cranking Fuel Injector Pulse Width C (ECT)" address="c7d76">
		<table name="Coolant Temperature" address="c73fc"/>
	</table>

	<table name="Cranking Fuel Injector Pulse Width D (ECT)" address="c7d96">
		<table name="Coolant Temperature" address="c73fc"/>
	</table>

	<table name="Cranking Fuel Injector Pulse Width E (ECT)" address="c7db6">
		<table name="Coolant Temperature" address="c73fc"/>
	</table>

	<table name="Cranking Fuel Injector Pulse Width F (ECT)" address="c7dd6">
		<table name="Coolant Temperature" address="c73fc"/>
	</table>

	<table name="Cranking Fuel Injector Pulse Width G (ECT)" address="c7df6">
		<table name="Coolant Temperature" address="c73fc"/>
	</table>

	<table name="Cranking Fuel IPW Compensation A (RPM)" address="c98c4">
		<table name="Engine Speed" address="c9894"/>
		<table name="Coolant Temperature" address="c98a8"/>
	</table>

	<table name="Cranking Fuel IPW Compensation B (RPM)" address="c9988">
		<table name="Engine Speed" address="c9950"/>
		<table name="Coolant Temperature" address="c9964" elements="9"/>
	</table>

	<table name="Cranking Fuel IPW Compensation (MAP)" address="c75f4">
		<table name="Manifold Pressure" address="c75cc"/>
	</table>

	<table name="Cranking Fuel IPW Compensation (Accelerator)" address="c7618">
		<table name="Accelerator Pedal Angle" address="c7600"/>
	</table>

	<table name="Cranking Fuel IPW Compensation (IAT)" address="c7634">
		<table name="Intake Temperature" address="c7620"/>
	</table>

	<table name="Throttle Tip-in Enrichment A" address="c9264">
		<table name="Throttle Angle Change" address="c921c"/>
	</table>

	<table name="Throttle Tip-in Enrichment B" address="c92d0">
		<table name="Throttle Angle Change" address="c9288"/>
	</table>

	<table name="Minimum Tip-in Enrichment Activation" address="c7290">
	</table>

	<table name="Minimum Tip-in Enrichment Activation (Throttle)" address="c728c">
	</table>

	<table name="Tip-in Enrichment Compensation (RPM)" address="c7bcc">
		<table name="Engine Speed" address="c7ba8"/>
	</table>

	<table name="Tip-in Enrichment Compensation (MRP)" address="c7bfc">
		<table name="Manifold Pressure" address="c7bd8"/>
	</table>

	<table name="Tip-in Enrichment Compensation A (ECT)" address="c7c05">
		<table name="Coolant Temperature" address="c73fc"/>
	</table>

	<table name="Tip-in Enrichment Compensation B (ECT)" address="c92f4">
		<table name="Coolant Temperature" address="c73fc"/>
	</table>

	<table name="Tip-in Enrichment Compensation C (ECT)" address="c9314">
		<table name="Coolant Temperature" address="c73fc"/>
	</table>

	<table name="Tip-in Enrichment Compensation D (ECT)" address="c9354">
		<table name="Coolant Temperature" address="c743c"/>
	</table>

	<table name="Tip-in Enrichment Compensation D (ECT) Activation" address="c7294">
	</table>

	<table name="Tip-in Enrichment Disable Applied Counter Threshold A (ECT)" address="c7c15">
		<table name="Coolant Temperature" address="c73fc"/>
	</table>

	<table name="Tip-in Enrichment Disable Applied Counter Threshold B (ECT)" address="c7c25">
		<table name="Coolant Temperature" address="c73fc"/>
	</table>

	<table name="Tip-in Enrichment Applied Counter Reset" address="c6bfd">
	</table>

	<table name="Tip-in Enrichment Disable Throttle Cumulative Threshold A (ECT)" address="c9374">
		<table name="Coolant Temperature" address="c73fc"/>
	</table>

	<table name="Tip-in Enrichment Disable Throttle Cumulative Threshold B (ECT)" address="c9394">
		<table name="Coolant Temperature" address="c73fc"/>
	</table>

	<table name="Tip-in Throttle Cumulative Reset" address="c6bfe">
	</table>

	<table name="A/F Learning #1 Limits" address="c6fa8">
	</table>

	<table name="A/F Learning #1 Airflow Ranges" address="c6fc8">
	</table>

	<table name="MAF Limit (Maximum)" address="c2350">
	</table>

	<table name="MAF Sensor Scaling" address="d1958">
		<table name="MAF sensor" address="d1898" elements="48"/>
	</table>

	<table name="Engine Load Limit (Maximum)" address="1e484">
	</table>

	<table name="Engine Load Compensation Cruise (MP)" address="c2d20">
		<table name="Manifold Pressure" address="c2cc4"/>
		<table name="Engine Speed" address="c2cf0"/>
	</table>

	<table name="Engine Load Compensation Non-Cruise (MP)" address="c2e00">
		<table name="Manifold Pressure" address="c2da4"/>
		<table name="Engine Speed" address="c2dd0"/>
	</table>

	<table name="Base Timing Primary Cruise" address="cde48">
		<table name="Engine Load" address="cddc4" elements="14"/>
		<table name="Engine Speed" address="cddfc" elements="19"/>
	</table>

	<table name="Base Timing Reference Cruise (AVCS related)" address="ce168">
		<table name="Engine Load" address="ce0e4" elements="14"/>
		<table name="Engine Speed" address="ce11c" elements="19"/>
	</table>

	<table name="Base Timing Primary Non-Cruise" address="cdfd8">
		<table name="Engine Load" address="cdf54" elements="14"/>
		<table name="Engine Speed" address="cdf8c" elements="19"/>
	</table>

	<table name="Base Timing Reference Non-Cruise (AVCS related)" address="ce2f8">
		<table name="Engine Load" address="ce274" elements="14"/>
		<table name="Engine Speed" address="ce2ac" elements="19"/>
	</table>

	<table name="Base Timing Idle (In-Gear)(Above Speed Threshold)_">
		<table name="Coolant Temperature" elements="4"/>
		<table name="Engine Speed" elements="10"/>
	</table>

	<table name="Base Timing Idle (In-Gear)(Above Speed Threshold)_" address="cdd9c">
		<table name="Engine Speed" address="cdd64"/>
		<table name="Coolant Temperature" address="cdd8c" scaling="DegreesF"/>
	</table>

	<table name="Base Timing Idle (In-Gear)(Below Speed Threshold)" address="cca5e">
		<table name="Engine Speed" address="cc8e0"/>
	</table>

	<table name="Base Timing Idle (Neutral)" address="ccabc">
		<table name="Engine Speed" address="cca98"/>
	</table>

	<table name="Base Timing Idle Vehicle Speed Threshold" address="cc54c">
	</table>

	<table name="Knock Correction Advance Max Cruise" address="ceb18">
		<table name="Engine Load" address="cea94" elements="14"/>
		<table name="Engine Speed" address="ceacc" elements="19"/>
	</table>

	<table name="Knock Correction Advance Max Non-Cruise" address="ceca8">
		<table name="Engine Load" address="cec24" elements="14"/>
		<table name="Engine Speed" address="cec5c" elements="19"/>
	</table>

	<table name="Timing Compensation (IAT)" address="ccbf8">
		<table name="Intake Temperature" address="ccbb8"/>
	</table>

	<table name="Timing Compensation (IAT) Activation" address="ce454">
		<table name="Engine Speed" address="ce404" elements="16"/>
		<table name="Engine Load" address="ce444" elements="4"/>
	</table>

	<table name="Timing Compensation A (ECT)" address="ccb75">
		<table name="Coolant Temperature" address="cc860"/>
	</table>

	<table name="Timing Compensation B (ECT)" address="ccb85">
		<table name="Coolant Temperature" address="cc860"/>
	</table>

	<table name="Timing Compensation C (ECT)" address="ccb95">
		<table name="Coolant Temperature" address="cc860"/>
	</table>

	<table name="Timing Compensation D (ECT)" address="ccba5">
		<table name="Coolant Temperature" address="cc860"/>
	</table>

	<table name="Timing Compensation Per Cylinder A" address="ce808">
		<table name="Engine Speed" address="ce7b4"/>
		<table name="Engine Load" address="ce7ec" elements="7"/>
	</table>

	<table name="Timing Compensation Per Cylinder B" address="ce8c0">
		<table name="Engine Speed" address="ce86c"/>
		<table name="Engine Load" address="ce8a4" elements="7"/>
	</table>

	<table name="Timing Compensation Per Cylinder C" address="ce978">
		<table name="Engine Speed" address="ce924"/>
		<table name="Engine Load" address="ce95c" elements="7"/>
	</table>

	<table name="Timing Compensation Per Cylinder D" address="cea30">
		<table name="Engine Speed" address="ce9dc"/>
		<table name="Engine Load" address="cea14" elements="7"/>
	</table>

	<table name="Timing Comp Minimum Load (Per Cylinder)" address="cc768">
	</table>

	<table name="Timing Comp Maximum RPM (Per Cylinder)" address="cc764">
	</table>

	<table name="Timing Comp Minimum Coolant Temp (Per Cylinder)" address="cc76c">
	</table>

	<table name="Feedback Correction Range (RPM)" address="cc774">
	</table>

	<table name="Feedback Correction Minimum Load_" address="cd2c0">
		<table name="Engine Speed" address="cd2b0"/>
	</table>

	<table name="Feedback Correction Retard Value_" address="cdc60">
		<table name="Engine Speed" address="cdc2c"/>
	</table>

	<table name="Feedback Correction Retard Limit" address="cc788">
	</table>

	<table name="Feedback Correction Negative Advance Value" address="cc78c">
	</table>

	<table name="Feedback Correction Negative Advance Delay_" address="cd2fc">
		<table name="Engine Speed" address="cd2c8"/>
	</table>

	<table name="Fine Correction Range (RPM)" address="cc840">
	</table>

	<table name="Fine Correction Range (Load)" address="cc850">
	</table>

	<table name="Fine Correction Rows (RPM)_" address="cc7e8">
	</table>

	<table name="Fine Correction Columns (Load)_" address="cc808">
	</table>

	<table name="Fine Correction Retard Value_" address="cdcc8">
		<table name="Engine Speed" address="cdc94"/>
	</table>

	<table name="Fine Correction Retard Limit" address="cc834">
	</table>

	<table name="Fine Correction Advance Value" address="cc830">
	</table>

	<table name="Fine Correction Advance Limit" address="cc82c">
	</table>

	<table name="Fine Correction Advance Delay" address="cc460">
	</table>

	<table name="Rough Correction Range (RPM)" address="cc7a4">
	</table>

	<table name="Rough Correction Range (Load)" address="cc7b4">
	</table>

	<table name="Rough Correction Learning Delay (Increasing)_" address="cd340">
		<table name="Engine Speed" address="cd318"/>
	</table>

	<table name="Advance Multiplier (Initial)" address="cc7c8">
	</table>

	<table name="Advance Multiplier Step Value" address="cc7cc">
	</table>

	<table name="Requested Torque (Accelerator Pedal) SI-DRIVE Sport" address="ddefc">
		<table name="Accelerator Pedal Angle" address="dde68" elements="17"/>
		<table name="Engine Speed" address="ddeac" elements="20"/>
	</table>

	<table name="Requested Torque (Accelerator Pedal) SI-DRIVE Sport Sharp" address="de238">
		<table name="Accelerator Pedal Angle" address="de1a4" elements="17"/>
		<table name="Engine Speed" address="de1e8" elements="20"/>
	</table>

	<table name="Requested Torque (Accelerator Pedal) SI-DRIVE Intelligent" address="de574">
		<table name="Accelerator Pedal Angle" address="de4e0" elements="17"/>
		<table name="Engine Speed" address="de524" elements="20"/>
	</table>

	<table name="Target Throttle Plate Position Cruise (Requested Torque Ratio)" address="dcd98">
		<table name="'Requested Torque (Accelerator Pedal)' to 'Requested Torque Base (RPM)'" address="dccd8" elements="28"/>
		<table name="Engine Speed" address="dcd48" elements="20"/>
	</table>

	<table name="Target Throttle Plate Position Non-Cruise (Requested Torque Ratio)" address="dd2b8">
		<table name="'Requested Torque (Accelerator Pedal)' to 'Requested Torque Base (RPM)'" address="dd1f8" elements="28"/>
		<table name="Engine Speed" address="dd268" elements="20"/>
	</table>

	<table name="Target Throttle Plate Position Maximum (Requested Torque Ratio)" address="dd7d8">
		<table name="'Requested Torque (Accelerator Pedal)' to 'Requested Torque Base (RPM)'" address="dd718" elements="28"/>
		<table name="Engine Speed" address="dd788" elements="20"/>
	</table>

	<table name="Rev Limit (Fuel Cut)" address="c7318">
	</table>

	<table name="Rev Limit Fuel Resume (MP)" address="c7320">
	</table>

	<table name="Speed Limiting Enable (Fuel Cut)" address="c7364">
	</table>

	<table name="Speed Limiting Disable (Fuel Cut)" address="c736c">
	</table>

	<table name="Speed Limiting A (Throttle) SI-DRIVE Sport/Sport Sharp" address="dc648">
	</table>

	<table name="Speed Limiting B (Throttle) SI-DRIVE Sport/Sport Sharp" address="dc660">
	</table>

	<table name="Speed Limiting A (Throttle) SI-DRIVE Intelligent" address="dc654">
	</table>

	<table name="Intake Temp Sensor Scaling" address="d16b0">
		<table name="Intake Temp Sensor" address="d1638"/>
	</table>

	<table name="Coolant Temp Sensor Scaling" address="d15c8">
		<table name="Coolant Temp Sensor" address="d1558"/>
	</table>

	<table name="Radiator Fan Modes A (ECT)" address="d1cf0">
	</table>

	<table name="Radiator Fan Modes B (ECT)" address="d1d00">
	</table>

	<table name="Radiator Fan Modes (Veh. Speed)" address="d1d10">
	</table>

	<table name="Idle Speed Target A" address="cfa18">
		<table name="Coolant Temperature" address="cf47c"/>
	</table>

	<table name="Idle Speed Target B" address="cfa58">
		<table name="Coolant Temperature" address="cf47c"/>
	</table>

	<table name="Idle Speed Target C" address="cfb38">
		<table name="Coolant Temperature" address="cf47c"/>
	</table>

	<table name="Idle Speed Target D" address="cfaf8">
		<table name="Coolant Temperature" address="cf47c"/>
	</table>

	<table name="Force Pass Readiness Monitors_" address="87090"/>

	<table name="(P0000) PASS CODE (NO DTC DETECTED)_" address="7bc5c"/>

	<table name="(P0000) PASS CODE (NO DTC DETECTED)" address="7bc5b"/>

	<table name="(P0026) OSV SOLENOID VALVE CIRCUIT RANGE/PERF B1" address="7bcad"/>

	<table name="(P0028) OSV SOLENOID VALVE CIRCUIT RANGE/PERF B2" address="7bcaa"/>

	<table name="(P0030) FRONT O2 SENSOR RANGE/PERF" address="7bc80"/>

	<table name="(P0031) FRONT O2 SENSOR LOW INPUT" address="7bc6a"/>

	<table name="(P0032) FRONT O2 SENSOR HIGH INPUT" address="7bc68"/>

	<table name="(P0037) REAR O2 SENSOR LOW INPUT" address="7bc69"/>

	<table name="(P0038) REAR O2 SENSOR HIGH INPUT" address="7bc67"/>

	<table name="(P0068) MAP SENSOR RANGE/PERF" address="7bc7b"/>

	<table name="(P0076) INTAKE VALVE CIRCUIT LOW (BANK 1)" address="7bcaf"/>

	<table name="(P0077) INTAKE VALVE CONTROL HIGH (BANK 1)" address="7bcae"/>

	<table name="(P0082) INTAKE VALVE CONTROL LOW (BANK 2)" address="7bcac"/>

	<table name="(P0083) INTAKE VALVE CONTROL HIGH (BANK 2)" address="7bcab"/>

	<table name="(P0101) MAF SENSOR RANGE/PERF" address="7bc7c"/>

	<table name="(P0102) MAF SENSOR LOW INPUT" address="7bc19"/>

	<table name="(P0103) MAF SENSOR HIGH INPUT" address="7bc1a"/>

	<table name="(P0107) MAP SENSOR LOW INPUT" address="7bc6b"/>

	<table name="(P0108) MAP SENSOR HIGH INPUT" address="7bc6c"/>

	<table name="(P0111) IAT SENSOR RANGE/PERF" address="7bc66"/>

	<table name="(P0112) IAT SENSOR LOW INPUT" address="7bc64"/>

	<table name="(P0113) IAT SENSOR HIGH INPUT" address="7bc65"/>

	<table name="(P0117) COOLANT TEMP SENSOR LOW INPUT" address="7bc22"/>

	<table name="(P0118) COOLANT TEMP SENSOR HIGH INPUT" address="7bc23"/>

	<table name="(P0122) TPS A LOW INPUT" address="7bc20"/>

	<table name="(P0123) TPS A HIGH INPUT" address="7bc21"/>

	<table name="(P0125) INSUFFICIENT COOLANT TEMP (FUELING)" address="7bc25"/>

	<table name="(P0126) INSUFFICIENT COOLANT TEMP (OPERATION)" address="7bcb9"/>

	<table name="(P0128) THERMOSTAT MALFUNCTION" address="7bc71"/>

	<table name="(P0131) FRONT O2 SENSOR LOW INPUT" address="7bc5e"/>

	<table name="(P0132) FRONT O2 SENSOR HIGH INPUT" address="7bc60"/>

	<table name="(P0133) FRONT O2 SENSOR SLOW RESPONSE" address="7bc48"/>

	<table name="(P0134) FRONT O2 SENSOR NO ACTIVITY" address="7bc7e"/>

	<table name="(P0137) REAR O2 SENSOR LOW VOLTAGE" address="7bc5d"/>

	<table name="(P0138) REAR O2 SENSOR HIGH VOLTAGE" address="7bc62"/>

	<table name="(P0139) REAR O2 SENSOR SLOW RESPONSE" address="7bc49"/>

	<table name="(P0140) REAR O2 SENSOR NO ACTIVITY" address="7bccc"/>

	<table name="(P0171) SYSTEM TOO LEAN" address="7bc52"/>

	<table name="(P0172) SYSTEM TOO RICH" address="7bc53"/>

	<table name="(P0181) FUEL TEMP SENSOR A RANGE/PERF" address="7bc31"/>

	<table name="(P0182) FUEL TEMP SENSOR A LOW INPUT" address="7bc2f"/>

	<table name="(P0183) FUEL TEMP SENSOR A HIGH INPUT" address="7bc30"/>

	<table name="(P0196) OIL TEMP SENSOR RANGE/PERF" address="7bcb0"/>

	<table name="(P0197) OIL TEMP SENSOR LOW" address="7bca6"/>

	<table name="(P0198) OIL TEMP SENSOR HIGH" address="7bcb1"/>

	<table name="(P0222) TPS B LOW INPUT" address="7bc88"/>

	<table name="(P0223) TPS B HIGH INPUT" address="7bc89"/>

	<table name="(P0301) MISFIRE CYLINDER 1" address="7bc54"/>

	<table name="(P0302) MISFIRE CYLINDER 2" address="7bc55"/>

	<table name="(P0303) MISFIRE CYLINDER 3" address="7bc56"/>

	<table name="(P0304) MISFIRE CYLINDER 4" address="7bc57"/>

	<table name="(P0327) KNOCK SENSOR 1 LOW INPUT" address="7bc1e"/>

	<table name="(P0328) KNOCK SENSOR 1 HIGH INPUT" address="7bc1f"/>

	<table name="(P0335) CRANKSHAFT POS. SENSOR A MALFUNCTION" address="7bc14"/>

	<table name="(P0336) CRANKSHAFT POS. SENSOR A RANGE/PERF" address="7bc15"/>

	<table name="(P0340) CAMSHAFT POS. SENSOR A MALFUNCTION" address="7bc17"/>

	<table name="(P0341) CAMSHAFT POS. SENSOR A RANGE/PERF" address="7bc16"/>

	<table name="(P0400) EGR FLOW" address="7bc51"/>

	<table name="(P0420) CAT EFFICIENCY BELOW THRESHOLD" address="7bc4e"/>

	<table name="(P0442) EVAP LEAK DETECTED (SMALL)" address="7bc4f"/>

	<table name="(P0447) EVAP VENT CONTROL CIRCUIT OPEN" address="7bc46"/>

	<table name="(P0448) EVAP VENT CONTROL CIRCUIT SHORTED" address="7bc47"/>

	<table name="(P0451) EVAP PRESSURE SENSOR RANGE/PERF" address="7bc2d"/>

	<table name="(P0452) EVAP PRESSURE SENSOR LOW INPUT" address="7bc2b"/>

	<table name="(P0453) EVAP PRESSURE SENSOR HIGH INPUT" address="7bc2c"/>

	<table name="(P0456) EVAP LEAK DETECTED (VERY SMALL)" address="7bc50"/>

	<table name="(P0457) EVAP LEAK DETECTED (FUEL CAP)" address="7bc5a"/>

	<table name="(P0458) EVAP PURGE VALVE CIRCUIT LOW" address="7bc43"/>

	<table name="(P0459) EVAP PURGE VALVE CIRCUIT HIGH" address="7bc44"/>

	<table name="(P0461) FUEL LEVEL SENSOR RANGE/PERF" address="7bc28"/>

	<table name="(P0462) FUEL LEVEL SENSOR LOW INPUT" address="7bc26"/>

	<table name="(P0463) FUEL LEVEL SENSOR HIGH INPUT" address="7bc27"/>

	<table name="(P0464) FUEL LEVEL SENSOR INTERMITTENT" address="7bc24"/>

	<table name="(P0500) VEHICLE SPEED SENSOR A" address="7bc1b"/>

	<table name="(P0506) IDLE CONTROL RPM LOWER THAN EXPECTED" address="7bc3b"/>

	<table name="(P0507) IDLE CONTROL RPM HIGH THAN EXPECTED" address="7bc3c"/>

	<table name="(P0512) STARTER REQUEST CIRCUIT" address="7bc2a"/>

	<table name="(P0604) CONTROL MODULE RAM ERROR" address="7bc18"/>

	<table name="(P0605) CONTROL MODULE ROM ERROR" address="7bc9d"/>

	<table name="(P0607) CONTROL MODULE PERFORMANCE" address="7bc90"/>

	<table name="(P0638) THROTTLE ACTUATOR RANGE/PERF" address="7bc8f"/>

	<table name="(P0700) TRANSMISSION CONTROL SYSTEM" address="7bca9"/>

	<table name="(P0851) NEUTRAL SWITCH INPUT LOW" address="7bc2e"/>

	<table name="(P0852) NEUTRAL SWITCH INPUT HIGH" address="7bc32"/>

	<table name="(P1152) FRONT O2 SENSOR RANGE/PERF LOW B1 S1" address="7bc4a"/>

	<table name="(P1153) FRONT O2 SENSOR RANGE/PERF HIGH B1 S1" address="7bc4b"/>

	<table name="(P1160) ABNORMAL RETURN SPRING" address="7bc8a"/>

	<table name="(P1400) FUEL TANK PRESSURE SOL. LOW" address="7bc41"/>

	<table name="(P1420) FUEL TANK PRESSURE SOL. HIGH INPUT" address="7bc42"/>

	<table name="(P1443) VENT CONTROL SOLENOID FUNCTION PROBLEM" address="7bc45"/>

	<table name="(P1491) PCV (BLOWBY) FUNCTION PROBLEM" address="7bc72"/>

	<table name="(P1492) EGR SOLENOID SIGNAL 1 MALFUNCTION (LOW)" address="7bc33"/>

	<table name="(P1493) EGR SOLENOID SIGNAL 1 MALFUNCTION (HIGH)" address="7bc34"/>

	<table name="(P1494) EGR SOLENOID SIGNAL 2 MALFUNCTION (LOW)" address="7bc35"/>

	<table name="(P1495) EGR SOLENOID SIGNAL 2 MALFUNCTION (HIGH)" address="7bc36"/>

	<table name="(P1496) EGR SIGNAL 3 CIRCUIT LOW" address="7bc37"/>

	<table name="(P1497) EGR SOLENOID SIGNAL 3 MALFUNCTION (HIGH)" address="7bc38"/>

	<table name="(P1498) EGR SIGNAL 4 CIRCUIT LOW" address="7bc39"/>

	<table name="(P1499) EGR SIGNAL 4 CIRCUIT HIGH" address="7bc3a"/>

	<table name="(P1519) IMRC STUCK CLOSED" address="7bcde"/>

	<table name="(P1520) IMRC CIRCUIT MALFUNCTION" address="7bcdd"/>

	<table name="(P1560) BACK-UP VOLTAGE MALFUNCTION" address="7bc73"/>

	<table name="(P1602) CONTROL MODULE PROGRAMMING ERROR" address="7bcce"/>

	<table name="(P1616) SBDS INTERACTIVE CODES" address="7bcdc"/>

	<table name="(P2096) POST CATALYST TOO LEAN B1" address="7bc8e"/>

	<table name="(P2097) POST CATALYST TOO RICH B1" address="7bc97"/>

	<table name="(P2101) THROTTLE ACTUATOR CIRCUIT RANGE/PERF" address="7bc8d"/>

	<table name="(P2102) THROTTLE ACTUATOR CIRCUIT LOW" address="7bc8b"/>

	<table name="(P2103) THROTTLE ACTUATOR CIRCUIT HIGH" address="7bc8c"/>

	<table name="(P2109) TPS A MINIMUM STOP PERF" address="7bc87"/>

	<table name="(P2122) TPS D CIRCUIT LOW INPUT" address="7bc94"/>

	<table name="(P2123) TPS D CIRCUIT HIGH INPUT" address="7bc95"/>

	<table name="(P2127) TPS E CIRCUIT LOW INPUT" address="7bc92"/>

	<table name="(P2128) TPS E CIRCUIT HIGH INPUT" address="7bc93"/>

	<table name="(P2135) TPS A/B VOLTAGE" address="7bc96"/>

	<table name="(P2138) TPS D/E VOLTAGE" address="7bc91"/>

	<table name="(P2227) BARO. PRESSURE CIRCUIT RANGE/PERF" address="7bcb8"/>

	<table name="(P2228) BARO. PRESSURE CIRCUIT LOW INPUT" address="7bcbb"/>

	<table name="(P2229) BARO. PRESSURE CIRCUIT HIGH INPUT" address="7bcba"/>

	<table name="(U0073) CAN COMMUNICATION BUS A OFF" address="7bcea"/>

	<table name="(U0101) CAN LOST COMMUNICATION WITH TCM" address="7bce7"/>

	<table name="(U0122) CAN LOST COMMUNICATION WITH VDC" address="7bce9"/>

	<table name="(U0140) CAN LOST COMMUNICATION WITH BIU" address="7bce5"/>

	<table name="(U0402) CAN INVALID DATA RECEIVED FROM TCM" address="7bce6"/>

	<table name="(U0416) CAN INVALID DATA RECEIVED FROM VDC" address="7bce8"/>

	<table name="(U0422) CAN INVALID DATA RECEIVED FROM BIU" address="7bce4"/>

	<table name="Ignition Dwell" address="d1bc0">
		<table name="Engine Speed" address="d1b78" elements="13"/>
		<table name="Battery Volts" address="d1bac"/>
	</table>

	<table name="Overrun Fueling RPM Resume Threshold" address="c93d4">
		<table name="Coolant Temperature" address="c73fc"/>
	</table>

	<table name="Overrun Enrich RPM Delta Activation" address="c7284">
	</table>

	<table name="Overrun initial injector enrichment (pulsewidth)" address="c7288">
	</table>

	<table name="Overrun Fueling Cut Counter RPM Threshold A" address="c72f4">
	</table>

	<table name="Overrun Fueling Cut Counter RPM Threshold B" address="c72fc">
	</table>

	<table name="Overrun Fueling Cut Counter RPM Threshold C" address="c7304">
	</table>

	<table name="Idle Airflow Min Target Decel Adder (RPM)" address="cf980">
		<table name="Engine Speed" address="cf940"/>
	</table>

	<table name="Idle Speed Stability A" address="d0820">
		<table name="Idle Speed Error" address="d07c0" elements="17"/>
		<table name="Engine Speed Delta" address="d0804" elements="7"/>
	</table>

	<table name="Idle Airflow Min Target Decel Adder Active Veh Speed A" address="cf04c"/>

	<table name="Idle Airflow Min Target Decel Initial Idle Min Airflow A" address="cf054"/>

	<table name="Idle Airflow Min Target Decel Initial Idle Activation Max Mode Counter" address="ceeec"/>

	<table name="Idle Airflow Min Target Decel Ramping Adder Decreasing" address="cf078"/>

	<table name="Idle Airflow Min Target Decel Ramping Adder Increasing" address="cf07c"/>

	<table name="AF 3 CL Target Compensation Limits" address="2e8cc"/>

	<table name="AF 3 Correction Limits" address="30164"/>

	<table name="AF 3 Learning Limits" address="30998"/>
</rom>
